dsparse/__init__.py
dsparse/main.py
dsparse/file_parsing/__init__.py
dsparse/file_parsing/element_types.py
dsparse/file_parsing/file_system.py
dsparse/file_parsing/non_vlm_file_parsing.py
dsparse/file_parsing/vlm.py
dsparse/file_parsing/vlm_file_parsing.py
dsparse/models/__init__.py
dsparse/models/types.py
dsparse/sectioning_and_chunking/__init__.py
dsparse/sectioning_and_chunking/chunking.py
dsparse/sectioning_and_chunking/semantic_sectioning.py
dsparse/tests/integration/test_vlm_file_parsing.py
dsparse/tests/unit/test_chunking_and_sectioning.py
dsparse/tests/unit/test_file_system.py
dsparse-0.0.2.dist-info/METADATA
dsparse-0.0.2.dist-info/WHEEL
dsparse-0.0.2.dist-info/top_level.txt
dsparse-0.0.2.dist-info/RECORD
