Metadata-Version: 2.1
Name: dsparse
Version: 0.0.2
Summary: Multi-modal file parsing and chunking
Author-email: Zach McCormick <zach@d-star.ai>, Nick McCormick <nick@d-star.ai>
Project-URL: Homepage, https://github.com/D-Star-AI/dsRAG/blob/main/dsrag/dsparse/README.md
Project-URL: Documentation, https://github.com/D-Star-AI/dsRAG/blob/main/dsrag/dsparse/README.md
Project-URL: Contact, https://github.com/D-Star-AI/dsRAG/blob/main/dsrag/dsparse/README.md
Classifier: Development Status :: 4 - Beta
Classifier: Intended Audience :: Developers
Classifier: Intended Audience :: Science/Research
Classifier: License :: OSI Approved :: MIT License
Classifier: Operating System :: OS Independent
Classifier: Programming Language :: Python :: 3.9
Classifier: Programming Language :: Python :: 3.10
Classifier: Programming Language :: Python :: 3.11
Classifier: Programming Language :: Python :: 3.12
Classifier: Topic :: Database
Classifier: Topic :: Software Development
Classifier: Topic :: Software Development :: Libraries
Classifier: Topic :: Software Development :: Libraries :: Application Frameworks
Classifier: Topic :: Software Development :: Libraries :: Python Modules
Requires-Python: >=3.9
Requires-Dist: aiohappyeyeballs==2.4.3
Requires-Dist: aiohttp==3.10.10
Requires-Dist: aiosignal==1.3.1
Requires-Dist: annotated-types==0.7.0
Requires-Dist: anthropic==0.37.1
Requires-Dist: anyio==4.6.2.post1
Requires-Dist: async-timeout==4.0.3
Requires-Dist: attrs==24.2.0
Requires-Dist: cachetools==5.5.0
Requires-Dist: certifi==2024.8.30
Requires-Dist: charset-normalizer==3.4.0
Requires-Dist: click==8.1.7
Requires-Dist: distro==1.9.0
Requires-Dist: docstring-parser==0.16
Requires-Dist: docx2txt==0.8
Requires-Dist: exceptiongroup==1.2.2
Requires-Dist: filelock==3.16.1
Requires-Dist: frozenlist==1.5.0
Requires-Dist: fsspec==2024.10.0
Requires-Dist: google-ai-generativelanguage==0.6.10
Requires-Dist: google-api-core[grpc]==2.21.0
Requires-Dist: google-api-python-client==2.149.0
Requires-Dist: google-auth==2.35.0
Requires-Dist: google-auth-httplib2==0.2.0
Requires-Dist: google-generativeai==0.8.3
Requires-Dist: googleapis-common-protos==1.65.0
Requires-Dist: grpcio==1.67.0
Requires-Dist: grpcio-status==1.67.0
Requires-Dist: h11==0.14.0
Requires-Dist: httpcore==1.0.6
Requires-Dist: httplib2==0.22.0
Requires-Dist: httpx==0.27.2
Requires-Dist: huggingface-hub==0.26.1
Requires-Dist: idna==3.10
Requires-Dist: instructor==1.6.3
Requires-Dist: jinja2==3.1.4
Requires-Dist: jiter==0.5.0
Requires-Dist: jsonpatch==1.33
Requires-Dist: jsonpointer==3.0.0
Requires-Dist: langchain-core==0.3.12
Requires-Dist: langchain-text-splitters==0.3.0
Requires-Dist: langsmith==0.1.137
Requires-Dist: markdown-it-py==3.0.0
Requires-Dist: markupsafe==3.0.2
Requires-Dist: mdurl==0.1.2
Requires-Dist: multidict==6.1.0
Requires-Dist: openai==1.52.2
Requires-Dist: orjson==3.10.10
Requires-Dist: packaging==24.1
Requires-Dist: pdf2image==1.17.0
Requires-Dist: pillow==11.0.0
Requires-Dist: propcache==0.2.0
Requires-Dist: proto-plus==1.25.0
Requires-Dist: protobuf==5.28.3
Requires-Dist: pyasn1==0.6.1
Requires-Dist: pyasn1-modules==0.4.1
Requires-Dist: pydantic==2.9.2
Requires-Dist: pydantic-core==2.23.4
Requires-Dist: pygments==2.18.0
Requires-Dist: pyparsing==3.2.0
Requires-Dist: pypdf2==3.0.1
Requires-Dist: pyyaml==6.0.2
Requires-Dist: requests==2.32.3
Requires-Dist: requests-toolbelt==1.0.0
Requires-Dist: rich==13.9.3
Requires-Dist: rsa==4.9
Requires-Dist: shellingham==1.5.4
Requires-Dist: sniffio==1.3.1
Requires-Dist: tenacity==9.0.0
Requires-Dist: tokenizers==0.20.1
Requires-Dist: tqdm==4.66.5
Requires-Dist: typer==0.12.5
Requires-Dist: typing-extensions==4.12.2
Requires-Dist: uritemplate==4.1.1
Requires-Dist: urllib3==2.2.3
Requires-Dist: yarl==1.16.0
Provides-Extra: s3
Requires-Dist: boto3>=1.34.142; extra == "s3"
Requires-Dist: botocore>=1.34.142; extra == "s3"
Provides-Extra: vertexai
Requires-Dist: vertexai>=1.70.0; extra == "vertexai"
